[
  { "refcode": "0000", "refperiod": "All Day" },
  { "refcode": "0030", "refperiod": "Early AM" },
  { "refcode": "0100", "refperiod": "Early AM" },
  { "refcode": "0130", "refperiod": "Early AM" },
  { "refcode": "0200", "refperiod": "Early AM" },
  { "refcode": "0230", "refperiod": "Early AM" },
  { "refcode": "0300", "refperiod": "Early AM" },
  { "refcode": "0330", "refperiod": "Early AM" },
  { "refcode": "0400", "refperiod": "Early AM" },
  { "refcode": "0430", "refperiod": "Early AM" },
  { "refcode": "0500", "refperiod": "Early AM" },
  { "refcode": "0530", "refperiod": "Early AM" },
  { "refcode": "0600", "refperiod": "Morning" },
  { "refcode": "0630", "refperiod": "Morning" },
  { "refcode": "0700", "refperiod": "Morning" },
  { "refcode": "0701", "refperiod": "Breakfast" },
  { "refcode": "0730", "refperiod": "Morning" },
  { "refcode": "0800", "refperiod": "Morning" },
  { "refcode": "0830", "refperiod": "Morning" },
  { "refcode": "0900", "refperiod": "Morning" },
  { "refcode": "0930", "refperiod": "Morning" },
  { "refcode": "1000", "refperiod": "Morning" },
  { "refcode": "1030", "refperiod": "Morning" },
  { "refcode": "1100", "refperiod": "Midday" },
  { "refcode": "1130", "refperiod": "Midday" },
  { "refcode": "1200", "refperiod": "Noon" },
  { "refcode": "1201", "refperiod": "Lunch" },
  { "refcode": "1230", "refperiod": "Midday" },
  { "refcode": "1300", "refperiod": "Midday" },
  { "refcode": "1330", "refperiod": "Afternoon" },
  { "refcode": "1400", "refperiod": "Afternoon" },
  { "refcode": "1430", "refperiod": "Afternoon" },
  { "refcode": "1500", "refperiod": "Afternoon" },
  { "refcode": "1530", "refperiod": "Afternoon" },
  { "refcode": "1600", "refperiod": "Afternoon" },
  { "refcode": "1630", "refperiod": "Afternoon" },
  { "refcode": "1700", "refperiod": "Afternoon" },
  { "refcode": "1730", "refperiod": "Afternoon" },
  { "refcode": "1800", "refperiod": "Evening" },
  { "refcode": "1801", "refperiod": "Dinner" },
  { "refcode": "1830", "refperiod": "Evening" },
  { "refcode": "1900", "refperiod": "Evening" },
  { "refcode": "1930", "refperiod": "Evening" },
  { "refcode": "2000", "refperiod": "Evening" },
  { "refcode": "2030", "refperiod": "Evening" },
  { "refcode": "2100", "refperiod": "Evening" },
  { "refcode": "2130", "refperiod": "Evening" },
  { "refcode": "2200", "refperiod": "Evening" },
  { "refcode": "2230", "refperiod": "Evening" },
  { "refcode": "2300", "refperiod": "Evening" },
  { "refcode": "2330", "refperiod": "Evening" },
  { "refcode": "2400", "refperiod": "Midnight" }
]
